Metadata-Version: 2.4
Name: types-networkx
Version: 3.6.1.20251220
Summary: Typing stubs for networkx
License-Expression: Apache-2.0
Project-URL: Homepage, https://github.com/python/typeshed
Project-URL: GitHub, https://github.com/python/typeshed
Project-URL: Changes, https://github.com/typeshed-internal/stub_uploader/blob/main/data/changelogs/networkx.md
Project-URL: Issue tracker, https://github.com/python/typeshed/issues
Project-URL: Chat, https://gitter.im/python/typing
Classifier: Programming Language :: Python :: 3
Classifier: Typing :: Stubs Only
Requires-Python: >=3.10
License-File: LICENSE
Requires-Dist: numpy>=1.20
Dynamic: license-file
